README.md
setup.py
mswadzba_school.egg-info/PKG-INFO
mswadzba_school.egg-info/SOURCES.txt
mswadzba_school.egg-info/dependency_links.txt
mswadzba_school.egg-info/top_level.txt
school/Classroom.py
school/Student.py