Metadata-Version: 2.1
Name: mswadzba-school
Version: 1.0.0
Summary: Sample School Lib
Home-page: UNKNOWN
License: UNKNOWN
Platform: UNKNOWN
